mcpi_mobs/__init__.py
mcpi_mobs/entities.py
mcpi_mobs/entity_file.py
mcpi_mobs-1.0.3.dist-info/LICENSE
mcpi_mobs-1.0.3.dist-info/METADATA
mcpi_mobs-1.0.3.dist-info/WHEEL
mcpi_mobs-1.0.3.dist-info/top_level.txt
mcpi_mobs-1.0.3.dist-info/RECORD
