Metadata-Version: 2.1
Name: mcpi-mobs
Version: 1.0.3
Summary: entities.dat editor for MCPE versions =>0.8.1
Home-page: UNKNOWN
Author: Will-777
Maintainer: LEHAtupointow
Maintainer-email: leha2@tuxfamily.org
License: UNKNOWN
Platform: UNKNOWN
Requires-Dist: amulet-nbt
